eip712/__init__.py
eip712/common/pydantic.py
eip712/convert/input_to_resolved.py
eip712/convert/resolved_to_instructions.py
eip712/model/base.py
eip712/model/input/contract.py
eip712/model/input/descriptor.py
eip712/model/input/message.py
eip712/model/instruction.py
eip712/model/resolved/contract.py
eip712/model/resolved/descriptor.py
eip712/model/resolved/message.py
eip712/model/schema.py
eip712/model/types.py
eip712/serialize.py
eip712/utils.py
eip712/VERSION
eip712_clearsign-4.1.0.dist-info/WHEEL
eip712_clearsign-4.1.0.dist-info/METADATA
eip712_clearsign-4.1.0.dist-info/licenses/LICENSE
eip712_clearsign-4.1.0.dist-info/RECORD
